[
  {
    "Электронная почта поставщика/производителя": "...",
    "ИНН поставщика/ производителя": "7720408452",
    "КПП": "772101001",
    "Формула": "ƒ = 72 руб./кг в т = (72*1000) = 72000 руб./т",
    "url": "https://yakutsk.pulscen.ru/products/bnm_55_60_bitum_neftyanoy_modifitsirovanny_kg_158787739",
    "Наименование поставщика/ производителя": "ООО \"СМТК\"",
    "Наименование ресурса по прейскуранту": "Битум БНМ-55/60 нефтяной модифицированный ГОСТ 9812-74",
    "Ценовое предложение, с НДС, руб.": "72 руб./кг",
    "Телефон поставщика/производителя": "+79180144220",
    "delivery_method": "Самовывоз",
    "Адрес поставщика/производителя/склада (место отгрузки)": "г Москва, Рязанский пр-кт, д 4А стр 2, помещ I, ком 29",
    "Адрес сайта в информационно-телекоммуникационной сети «Интернет» поставщика/производителя": "https://www.xn--j1adof.xn--p1acf/goods/158787739-bnm_55_60_bitum_neftyanoy_modifitsirovanny_kg",
    "Цена зафиксирована на дату": "2025-08-18 17:02:19",
    "Прейскурант": "01.2.01.02-0021_1_2025_3.pdf",
    "Индекс": "22",
    "note": "OK"
  },
  {
    "Электронная почта поставщика/производителя": "не указан",
    "ИНН поставщика/ производителя": "не указан",
    "КПП": "не указан",
    "Формула": "не указан",
    "url": "https://yakutsk.pulscen.ru/products/bitum_neftyanoy_modifitsirovanny_bnm_55_60_312888548",
    "Наименование поставщика/ производителя": "не указан",
    "Наименование ресурса по прейскуранту": "Битум нефтяной модифицированный БНМ 55/60",
    "Ценовое предложение, с НДС, руб.": "от 80 руб./кг",
    "Телефон поставщика/производителя": "+78432508884",
    "delivery_method": "Самовывоз",
    "Адрес поставщика/производителя/склада (место отгрузки)": "не указан",
    "Адрес сайта в информационно-телекоммуникационной сети «Интернет» поставщика/производителя": "https://www.xn---116-53da8ayafzgvzghqg1o.xn--p1ai/goods/312888548-bitum_neftyanoy_modifitsirovanny_bnm_55_60",
    "Цена зафиксирована на дату": "2025-08-18 17:02:52",
    "Прейскурант": "01.2.01.02-0021_2_2025_3.pdf",
    "Индекс": "23",
    "note": "OK"
  },
  {
    "Электронная почта поставщика/производителя": "...",
    "ИНН поставщика/ производителя": "5906181940",
    "КПП": "590601001",
    "Формула": "ƒ = 15 руб. в т = ( 15*1 ) = 15",
    "url": "https://yakutsk.pulscen.ru/products/bitum_bnm_55_60_170198939",
    "Наименование поставщика/ производителя": "ООО ЗИП \"ГИДРОЗАЩИТА\"",
    "Наименование ресурса по прейскуранту": "Битум БНМ 55/60",
    "Ценовое предложение, с НДС, руб.": "от 15 руб.",
    "Телефон поставщика/производителя": "+78005338860",
    "delivery_method": "Самовывоз",
    "Адрес поставщика/производителя/склада (место отгрузки)": "г Пермь, ул Соликамская, д 283, офис 402",
    "Адрес сайта в информационно-телекоммуникационной сети «Интернет» поставщика/производителя": "https://www.bitumprom.ru/goods/170198939-bitum_bnm_55_60",
    "Цена зафиксирована на дату": "2025-08-18 17:03:25",
    "Прейскурант": "01.2.01.02-0021_3_2025_3.pdf",
    "Индекс": "24",
    "note": "OK"
  }
]